tfplugin_proto/__init__.py
tfplugin_proto/py.typed
tfplugin_proto/tfplugin5_0_pb2.py
tfplugin_proto/tfplugin5_0_pb2.pyi
tfplugin_proto/tfplugin5_0_pb2_grpc.py
tfplugin_proto/tfplugin5_1_pb2.py
tfplugin_proto/tfplugin5_1_pb2.pyi
tfplugin_proto/tfplugin5_1_pb2_grpc.py
tfplugin_proto/tfplugin5_2_pb2.py
tfplugin_proto/tfplugin5_2_pb2.pyi
tfplugin_proto/tfplugin5_2_pb2_grpc.py
tfplugin_proto/tfplugin5_3_pb2.py
tfplugin_proto/tfplugin5_3_pb2.pyi
tfplugin_proto/tfplugin5_3_pb2_grpc.py
tfplugin_proto/tfplugin5_4_pb2.py
tfplugin_proto/tfplugin5_4_pb2.pyi
tfplugin_proto/tfplugin5_4_pb2_grpc.py
tfplugin_proto/tfplugin5_5_pb2.py
tfplugin_proto/tfplugin5_5_pb2.pyi
tfplugin_proto/tfplugin5_5_pb2_grpc.py
tfplugin_proto/tfplugin6_0_pb2.py
tfplugin_proto/tfplugin6_0_pb2.pyi
tfplugin_proto/tfplugin6_0_pb2_grpc.py
tfplugin_proto/tfplugin6_1_pb2.py
tfplugin_proto/tfplugin6_1_pb2.pyi
tfplugin_proto/tfplugin6_1_pb2_grpc.py
tfplugin_proto/tfplugin6_2_pb2.py
tfplugin_proto/tfplugin6_2_pb2.pyi
tfplugin_proto/tfplugin6_2_pb2_grpc.py
tfplugin_proto/tfplugin6_3_pb2.py
tfplugin_proto/tfplugin6_3_pb2.pyi
tfplugin_proto/tfplugin6_3_pb2_grpc.py
tfplugin_proto/tfplugin6_4_pb2.py
tfplugin_proto/tfplugin6_4_pb2.pyi
tfplugin_proto/tfplugin6_4_pb2_grpc.py
tfplugin_proto/tfplugin6_5_pb2.py
tfplugin_proto/tfplugin6_5_pb2.pyi
tfplugin_proto/tfplugin6_5_pb2_grpc.py
tfplugin_proto_all-0.1.0.dist-info/LICENSE
tfplugin_proto_all-0.1.0.dist-info/METADATA
tfplugin_proto_all-0.1.0.dist-info/WHEEL
tfplugin_proto_all-0.1.0.dist-info/RECORD
